log_calculator/__init__.py
log_calculator-0.1.0.dist-info/METADATA
log_calculator-0.1.0.dist-info/WHEEL
log_calculator-0.1.0.dist-info/RECORD
