Metadata-Version: 2.1
Name: log-calculator
Version: 0.1.0
Summary: 
Author: rebuglio
Author-email: m.rebuglio@gmail.com
Requires-Python: >=3.11,<4.0
Classifier: Programming Language :: Python :: 3
Classifier: Programming Language :: Python :: 3.11
Classifier: Programming Language :: Python :: 3.12
Requires-Dist: pandas (>=2.2.3,<3.0.0)
